text_studio/__init__.py
text_studio/action.py
text_studio/annotator.py
text_studio/data_loader.py
text_studio/dataset.py
text_studio/model.py
text_studio/pipeline.py
text_studio-0.0.1a0.dist-info/LICENSE
text_studio-0.0.1a0.dist-info/METADATA
text_studio-0.0.1a0.dist-info/WHEEL
text_studio-0.0.1a0.dist-info/top_level.txt
text_studio-0.0.1a0.dist-info/RECORD
