Metadata-Version: 2.1
Name: text-studio
Version: 0.0.1a0
Summary: Python package that powers the TextStudio development environment where users can explore, process, model, and visualize textual data.
Home-page: https://github.com/tevnpowers/text-studio
Author: Tev'n Powers
Author-email: tevnpowers@gmail.com
License: UNKNOWN
Download-URL: https://pypi.org/project/text-studio/#files
Project-URL: Bug Tracker, https://github.com/tevnpowers/text-studio/issues
Project-URL: Documentation, https://github.com/tevnpowers/text-studio/tree/master/docs
Project-URL: Source Code, https://github.com/tevnpowers/text-studio
Platform: UNKNOWN
Classifier: Programming Language :: Python :: 3
Classifier: License :: OSI Approved :: MIT License
Classifier: Operating System :: OS Independent
Requires-Python: >=3.6
